setup.py
bin/toast
toaster/__init__.py
toaster/convertible.py
toaster/page.py
toaster/plugin.py
toaster/post.py
toaster/site.py
toaster.egg-info/PKG-INFO
toaster.egg-info/SOURCES.txt
toaster.egg-info/dependency_links.txt
toaster.egg-info/requires.txt
toaster.egg-info/top_level.txt
toaster/converters/__init__.py
toaster/converters/markdownconverter.py