Metadata-Version: 1.0
Name: toaster
Version: 0.0.4
Summary: A static blog generator inspired by Jekyll.
Home-page: https://github.com/ryancole/toaster
Author: Ryan Cole
Author-email: ryan@rycole.com
License: MIT
Keywords: toaster static blog jekyll
Platform: UNKNOWN
